full_adder.v
//Full bit adder

module full_adder
(
    input i_a,
    input i_b,
    input i_c,
    output o_s,
    output o_c   
);

assign {o_c, o_s} = i_a + i_b + i_c ;

endmodule

adder.v
//Carry Lookahead Adder

`include "full_adder.v"

module adder
(
    input [3:0] i_a,
    input [3:0] i_b,
    input       i_c,
    output [4:0] o_s
);

    wire [3:0] w_gc;
    wire [3:0] w_pc;
    wire [4:0] w_c;
    wire [3:0] w_sum;

    //Produce Generated Carry
    assign w_gc = i_a & i_b;

    //Produce Propogate Carry
    assign w_pc = i_a | i_b;

    //Predicate CARRY bits
    assign w_c[0] = i_c;        //Input Carry
    assign w_c[1] = w_gc[0] | (w_pc[0] & w_c[0]);
    assign w_c[2] = w_gc[1] | (w_pc[1] & w_c[1]);
    assign w_c[3] = w_gc[2] | (w_pc[2] & w_c[2]);
    assign w_c[4] = w_gc[3] | (w_pc[3] & w_c[3]);

    //Instants the full adder module

    full_adder bit_0
    (
        .i_a(i_a[0]),
        .i_b(i_b[0]),
        .i_c(w_c[0]),
        .o_s(w_sum[0]),
        .o_c()   
    );

    full_adder bit_1
    (
        .i_a(i_a[1]),
        .i_b(i_b[1]),
        .i_c(w_c[1]),
        .o_s(w_sum[1]),
        .o_c()   
    );

    full_adder bit_2
    (
        .i_a(i_a[2]),
        .i_b(i_b[2]),
        .i_c(w_c[2]),
        .o_s(w_sum[2]),
        .o_c()   
    );

    full_adder bit_3
    (
        .i_a(i_a[3]),
        .i_b(i_b[3]),
        .i_c(w_c[3]),
        .o_s(w_sum[3]),
        .o_c()   
    );

    //Assigning output 
    assign o_s = {w_c[4], w_sum};

    // Dump waves
    initial begin
        $dumpfile("dump.vcd");
        $dumpvars(1, adder);
    end
endmodule

dump.vcd
$date
	Thu Jun 17 17:44:21 2021
$end
$version
	Icarus Verilog
$end
$timescale
	1ps
$end
$scope module adder $end
$var wire 4 ! i_a [3:0] $end
$var wire 4 " i_b [3:0] $end
$var wire 1 # i_c $end
$var wire 4 $ w_gc [3:0] $end
$var wire 4 % w_pc [3:0] $end
$var wire 4 & w_sum [3:0] $end
$var wire 5 ' w_c [4:0] $end
$var wire 5 ( o_s [4:0] $end
$upscope $end
$enddefinitions $end
#0
$dumpvars
b10000 (
b11111 '
b0 &
b1111 %
b0 $
1#
b1010 "
b101 !
$end
#2001
b1100 (
b1100 &
b1100 %
b0 '
0#
b1100 !
b0 "
#4001
b100 '
b1101 (
b1101 &
b10 $
b1011 %
b11 !
b1010 "
#6001
b11000 '
b10010 (
b10 &
b100 $
b1110 %
b1110 !
b100 "
#8001
b0 '
b111 (
b111 &
b0 $
b111 %
b110 !
b1 "
#10001
b11100 '
b10001 (
b1 &
b10 $
b1111 %
b1010 !
b111 "
#12001
b10000 '
b10111 (
b111 &
b1000 $
b1101 !
b1010 "
#14001
b1110 '
b1010 (
b1010 &
b11 $
b111 %
b111 !
b11 "
#16001
b1000 (
b1000 &
b1 $
b101 !
#18001
b11100 '
b10001 (
b1 &
b10 $
b1111 %
b111 !
b1010 "
#20001
b0 '
b1011 (
b1011 &
b0 $
b1011 %
b0 !
b1011 "
